optionaldict/__init__.py
optionaldict/__init__.pyi
optionaldict/py.typed
optionaldict-0.1.2.dist-info/LICENSE
optionaldict-0.1.2.dist-info/METADATA
optionaldict-0.1.2.dist-info/WHEEL
optionaldict-0.1.2.dist-info/top_level.txt
optionaldict-0.1.2.dist-info/RECORD
